{
  "demo_name": "screener",
  "total_duration_sec": 67.0,
  "segments": [
    {
      "segment_id": "screener_story_01",
      "step": 1,
      "type": "primary",
      "offset_sec": 0.0,
      "budget_sec": 7.0,
      "text": "Most people pick stocks on gut. Let's change that. Open Screener. Search Reliance.",
      "fallback_text": "Most people pick stocks on gut. Let's change that. Open Screener. Search Reliance.",
      "subtitle": "Open Screener and type Reliance Industries.",
      "target_window_end_sec": 7.0,
      "source_start_step": 1,
      "source_end_step": 2,
      "source_start_sec": 0.0,
      "source_end_sec": 18.788,
      "spoken_text": "Most people pick stocks on gut. Let's change that. Open Screener. Search Reliance.",
      "clip_duration_sec": 5.731,
      "clip_path": "C:\\Users\\admin\\Downloads\\video_tutorial\\output\\narration_timeline_1k_kc0pu\\screener_story_01_primary_normalized.wav",
      "required_speedup": 0.819,
      "start_sec": 0.0,
      "end_sec": 5.731
    },
    {
      "segment_id": "screener_story_02",
      "step": 3,
      "type": "primary",
      "offset_sec": 7.0,
      "budget_sec": 7.0,
      "text": "There it is. Click Reliance. Now the real checklist begins.",
      "fallback_text": "There it is. Click Reliance. Now the real checklist begins.",
      "subtitle": "Click Reliance and open the company page.",
      "target_window_end_sec": 14.0,
      "source_start_step": 3,
      "source_end_step": 3,
      "source_start_sec": 18.788,
      "source_end_sec": 25.105,
      "spoken_text": "There it is. Click Reliance. Now the real checklist begins.",
      "clip_duration_sec": 4.931,
      "clip_path": "C:\\Users\\admin\\Downloads\\video_tutorial\\output\\narration_timeline_1k_kc0pu\\screener_story_02_primary_normalized.wav",
      "required_speedup": 0.704,
      "start_sec": 7.0,
      "end_sec": 11.931
    },
    {
      "segment_id": "screener_story_03",
      "step": 4,
      "type": "primary",
      "offset_sec": 14.0,
      "budget_sec": 11.0,
      "text": "First, check the big three at the top: Market Cap, P/E, and ROCE. Then open quarterly results and make sure profits are actually climbing.",
      "fallback_text": "First, check the big three at the top: Market Cap, P/E, and ROCE. Then open quarterly results and make sure profits are actually climbing.",
      "subtitle": "Check the top metrics, then open quarterly results.",
      "target_window_end_sec": 25.0,
      "source_start_step": 4,
      "source_end_step": 5,
      "source_start_sec": 25.105,
      "source_end_sec": 33.46,
      "spoken_text": "First, check the big three at the top: Market Cap, P/E, and ROCE. Then open quarterly results and make sure profits are actually climbing.",
      "clip_duration_sec": 10.371,
      "clip_path": "C:\\Users\\admin\\Downloads\\video_tutorial\\output\\narration_timeline_1k_kc0pu\\screener_story_03_primary_normalized.wav",
      "required_speedup": 0.943,
      "start_sec": 14.0,
      "end_sec": 24.371
    },
    {
      "segment_id": "screener_story_04",
      "step": 6,
      "type": "primary",
      "offset_sec": 25.0,
      "budget_sec": 11.0,
      "text": "Next, sweep through Profit and Loss and the Balance Sheet. Revenues should rise, earnings should look clean, and debt should stay under control.",
      "fallback_text": "Next, sweep through Profit and Loss and the Balance Sheet. Revenues should rise, earnings should look clean, and debt should stay under control.",
      "subtitle": "Check Profit and Loss, then the Balance Sheet.",
      "target_window_end_sec": 36.0,
      "source_start_step": 6,
      "source_end_step": 7,
      "source_start_sec": 33.46,
      "source_end_sec": 43.557,
      "spoken_text": "Next, sweep through Profit and Loss and the Balance Sheet. Revenues should rise, earnings should look clean, and debt should stay under control.",
      "clip_duration_sec": 8.531,
      "clip_path": "C:\\Users\\admin\\Downloads\\video_tutorial\\output\\narration_timeline_1k_kc0pu\\screener_story_04_primary_normalized.wav",
      "required_speedup": 0.776,
      "start_sec": 25.0,
      "end_sec": 33.531
    },
    {
      "segment_id": "screener_story_05",
      "step": 8,
      "type": "primary",
      "offset_sec": 36.0,
      "budget_sec": 7.0,
      "text": "No stock idea yet? Hit Screens. That is your cheat code.",
      "fallback_text": "No stock idea yet? Hit Screens. That is your cheat code.",
      "subtitle": "No stock idea yet? Click Screens.",
      "target_window_end_sec": 43.0,
      "source_start_step": 8,
      "source_end_step": 8,
      "source_start_sec": 43.557,
      "source_end_sec": 50.039,
      "spoken_text": "No stock idea yet? Hit Screens. That is your cheat code.",
      "clip_duration_sec": 4.251,
      "clip_path": "C:\\Users\\admin\\Downloads\\video_tutorial\\output\\narration_timeline_1k_kc0pu\\screener_story_05_primary_normalized.wav",
      "required_speedup": 0.607,
      "start_sec": 36.0,
      "end_sec": 40.251
    },
    {
      "segment_id": "screener_story_06",
      "step": 9,
      "type": "primary",
      "offset_sec": 43.0,
      "budget_sec": 13.0,
      "text": "Now click Show all screens and find this exact filter: High Growth, High RoE, Low PE. Fast growers, efficient businesses, sane valuation. Open it.",
      "fallback_text": "Now click Show all screens and find this exact filter: High Growth, High RoE, Low PE. Fast growers, efficient businesses, sane valuation. Open it.",
      "subtitle": "Find and open the High Growth, High RoE, Low PE screen.",
      "target_window_end_sec": 56.0,
      "source_start_step": 9,
      "source_end_step": 11,
      "source_start_sec": 50.039,
      "source_end_sec": 65.391,
      "spoken_text": "Now click Show all screens and find this exact filter: High Growth, High RoE, Low PE. Fast growers, efficient businesses, sane valuation. Open it.",
      "clip_duration_sec": 12.771,
      "clip_path": "C:\\Users\\admin\\Downloads\\video_tutorial\\output\\narration_timeline_1k_kc0pu\\screener_story_06_primary_normalized.wav",
      "required_speedup": 0.982,
      "start_sec": 43.0,
      "end_sec": 55.771
    },
    {
      "segment_id": "screener_story_07",
      "step": 12,
      "type": "primary",
      "offset_sec": 56.0,
      "budget_sec": 11.0,
      "text": "The filter has done the hunting. Ganesh Infra makes the shortlist, so open it and run the same four-point check. That is how you go from guessing to investing with a plan.",
      "fallback_text": "The filter has done the hunting. Ganesh Infra makes the shortlist, so open it and run the same four-point check. That is how you go from guessing to investing with a plan.",
      "subtitle": "Open Ganesh Infra and run the same four-point check.",
      "target_window_end_sec": 67.0,
      "source_start_step": 12,
      "source_end_step": 13,
      "source_start_sec": 65.391,
      "source_end_sec": 81.877,
      "spoken_text": "The filter has done the hunting. Ganesh Infra makes the shortlist, so open it and run the same four-point check. That is how you go from guessing to investing with a plan.",
      "clip_duration_sec": 10.691,
      "clip_path": "C:\\Users\\admin\\Downloads\\video_tutorial\\output\\narration_timeline_1k_kc0pu\\screener_story_07_primary_normalized.wav",
      "required_speedup": 0.972,
      "start_sec": 56.0,
      "end_sec": 66.691
    }
  ]
}